AppOpener/__init__.py
MacAppOpener-0.0.5.dist-info/LICENCE.txt
MacAppOpener-0.0.5.dist-info/METADATA
MacAppOpener-0.0.5.dist-info/WHEEL
MacAppOpener-0.0.5.dist-info/top_level.txt
MacAppOpener-0.0.5.dist-info/RECORD
