Metadata-Version: 2.1
Name: MacAppOpener
Version: 0.0.5
Summary: A simple python module that offers a MacOS alternative to the AppOpener module.
Home-page: 
Author: Ryann Elguessab
Author-email: ryannelguessab@gmail.com
License: MIT
Keywords: appMacOS
Classifier: Development Status :: 5 - Production/Stable
Classifier: Intended Audience :: Education
Classifier: Operating System :: Microsoft :: Windows :: Windows 10
Classifier: License :: OSI Approved :: MIT License
Classifier: Programming Language :: Python :: 3
License-File: LICENCE.txt
